{
    "error": false,
    "version": "thirteen",
    "filename": "PixelOS_courbet-13.0-20221125-2252.zip",
    "datetime": 1669416699,
    "size": 2159746312,
    "url": "https://sourceforge.net/projects/pixelos-releases/files/thirteen/courbet/PixelOS_courbet-13.0-20221125-2252.zip",
    "github_releases_url": "https://sourceforge.net/projects/pixelos-releases/files/thirteen/courbet/PixelOS_courbet-13.0-20221125-2252.zip",
    "filehash": "7fa6102d8c31938b7429d9732c1f99e5",
    "id": "7fa6102d8c31938b7429d9732c1f99e5",
    "maintainers": [
        {
            "main_maintainer": false,
            "github_username": "vantoman",
            "name": "Vantom"
        },
        {
            "main_maintainer": false,
            "github_username": "basamaryan",
            "name": "Aryan"
        }
    ],
    "donate_url": "",
    "website_url": "https://pixelos.net/",
    "news_url": "https://blog.pixelos.net/",
    "forum_url": ""
}