{
    "error": false,
    "version": "thirteen",
    "filename": "PixelOS_davinci-13.0-20221029-0229.zip",
    "datetime": 1667010520,
    "size": 2000342067,
    "url": "https://sourceforge.net/projects/pixelos-releases/files/thirteen/davinci/PixelOS_davinci-13.0-20221029-0229.zip",
    "github_releases_url": "https://github.com/PixelOS-Releases/releases-public/releases/download/2022-10-29/PixelOS_davinci-13.0-20221029-0229.zip",
    "filehash": "8156b8b8ccd6cd1ca862da059ab5c367",
    "id": "8156b8b8ccd6cd1ca862da059ab5c367",
    "maintainers": [
        {
            "main_maintainer": false,
            "github_username": "vansh123456",
            "name": "Vansh"
        },
        {
            "main_maintainer": false,
            "github_username": "basamaryan",
            "name": "Aryan"
        }
    ],
    "donate_url": "",
    "website_url": "https://pixelos.net/",
    "news_url": "https://blog.pixelos.net/",
    "forum_url": ""
}