{
    "error": false,
    "version": "twelve",
    "filename": "PixelOS_davinci-12.1-20220409-2021.zip",
    "datetime": 1649535660,
    "size": 1835197293,
    "url": "https://github.com/PixelOS-Releases/releases-public/releases/download/2022-04-10/PixelOS_davinci-12.1-20220409-2021.zip",
    "filehash": "13e87cbefc07befc76395fe986bc7b9e",
    "id": "13e87cbefc07befc76395fe986bc7b9e",
    "maintainers": [
        {
            "main_maintainer": false,
            "github_username": "vansh123456",
            "name": "Vansh"
        }
    ],
    "donate_url": "",
    "website_url": "https://pixelos.vercel.app/",
    "news_url": "https://t.me/PixelOSOfficial",
    "forum_url": ""
}