{
    "error": false,
    "version": "fourteen",
    "filename": "PixelOS_diting-14.0-20240417-1453.zip",
    "datetime": 1713365490,
    "size": 2560683870,
    "url": "https://sourceforge.net/projects/pixelos-releases/files/fourteen/diting/PixelOS_diting-14.0-20240417-1453.zip",
    "github_releases_url": "https://sourceforge.net/projects/pixelos-releases/files/fourteen/diting/PixelOS_diting-14.0-20240417-1453.zip",
    "filehash": "312d4222fa770ec73df9cab7bebd6e0e",
    "id": "312d4222fa770ec73df9cab7bebd6e0e",
    "maintainers": [
        {
            "main_maintainer": false,
            "github_username": "bheatleyyy",
            "name": "Sugakesshaa"
        }
    ],
    "donate_url": "",
    "website_url": "https://pixelos.net/",
    "news_url": "https://blog.pixelos.net/",
    "forum_url": ""
}