{
    "error": false,
    "version": "twelve",
    "filename": "PixelOS_starlte-12.1-20220709-1151.zip",
    "datetime": 1657367460,
    "size": 1556125346,
    "url": "https://sourceforge.net/projects/pixelos-releases/files/twelve/starlte/PixelOS_starlte-12.1-20220709-1151.zip",
    "github_releases_url": "https://github.com/PixelOS-Releases/releases-public/releases/download/2022-07-11/PixelOS_starlte-12.1-20220709-1151.zip",
    "filehash": "40dafadfd30a9ea18dc02958cd530cd7",
    "id": "40dafadfd30a9ea18dc02958cd530cd7",
    "maintainers": [
        {
            "main_maintainer": false,
            "github_username": "Seraphine3",
            "name": "Mia Ryujin"
        }
    ],
    "donate_url": "",
    "website_url": "https://pixelos.vercel.app/",
    "news_url": "https://t.me/PixelOSOfficial",
    "forum_url": "https://forum.xda-developers.com/t/rom-12l-oss-official-pixel-os-for-samsung-galaxy-s9-s9.4438215/#post-87043351/"
}