{
    "beyond2lte": 191,
    "mido": 15420,
    "violet": 9172,
    "d2x": 124,
    "alioth": 32354,
    "lime": 0,
    "miatoll": 17939,
    "r5x": 4798,
    "munch": 4561,
    "davinci": 21917,
    "RMX2020": 7514,
    "beyond1lte": 175,
    "dubai": 570,
    "G": 310,
    "d2s": 249,
    "vayu": 13465,
    "beyondx": 114,
    "juice": 14808,
    "gauguin": 7970,
    "sweet": 107434,
    "surya": 36217,
    "bitra": 1132,
    "toco": 5371,
    "cepheus": 18939,
    "beryllium": 40435,
    "d1": 57,
    "courbet": 9081,
    "martini": 3532,
    "lisa": 52405,
    "citrus": 0,
    "beyond0lte": 119,
    "mojito": 55854,
    "ginkgo": 50071,
    "yogurt": 146,
    "hotdogg": 745,
    "RMX1941": 1412,
    "whyred": 3466,
    "star2lte": 533,
    "hotdog": 1093,
    "crownlte": 411,
    "starlte": 257
}