{
    "zeus": 7682,
    "aston": 12103,
    "pipa": 5823,
    "davinci": 60180,
    "gauguin": 38264,
    "beryllium": 157333,
    "lunaa": 11644,
    "cepheus": 85933,
    "lisa": 135863,
    "oscar": 15384,
    "peridot": 6822,
    "RMX2020": 21916,
    "sunny": 61075,
    "cancunf": 4101,
    "sweet": 314001,
    "porsche": 13859,
    "alioth": 182210,
    "sky": 18216,
    "munch": 19484,
    "tundra": 3222,
    "miatoll": 81208,
    "bitra": 4641,
    "courbet": 24791,
    "marble": 19663,
    "d1x": 868,
    "guamp": 3010,
    "beyondx": 2982,
    "grus": 3317,
    "RMX2001L1": 9521,
    "ginkgo": 141124,
    "diting": 4986,
    "beyond2lte": 9301,
    "beyond0lte": 7233,
    "d1": 2961,
    "pdx206": 5030,
    "r5x": 7189,
    "apollo": 17151,
    "mido": 24291,
    "martini": 21522,
    "beyond1lte": 8440,
    "d2x": 4450,
    "toco": 20021,
    "G": 4112,
    "f62": 4189,
    "salaa": 7450,
    "d2s": 7077,
    "cupid": 9020,
    "vayu": 71771,
    "spaced": 1923,
    "cheetah": 1822,
    "violet": 23932,
    "flame": 3552,
    "yogurt": 1492,
    "surya": 54727,
    "citrus": 4030,
    "panther": 3421,
    "dubai": 2048,
    "coral": 2123,
    "lancelot": 9246,
    "lime": 6363,
    "hotdogg": 992,
    "RMX1941": 2638,
    "whyred": 4676,
    "starlte": 837,
    "crownlte": 1005,
    "hotdog": 1314,
    "star2lte": 1482,
    "juice": 8761,
    "mojito": 22051
}