{
    "martini": 17572,
    "zeus": 2905,
    "apollo": 7186,
    "d1x": 3,
    "gauguin": 28499,
    "beyond1lte": 3761,
    "vayu": 50750,
    "guamp": 718,
    "sweet": 258584,
    "porsche": 11212,
    "mido": 22513,
    "miatoll": 61789,
    "tundra": 1928,
    "RMX2001L1": 5501,
    "beyond0lte": 2991,
    "sky": 8701,
    "munch": 18547,
    "sunny": 38048,
    "d2x": 2249,
    "d1": 1392,
    "salaa": 4747,
    "f62": 1794,
    "cepheus": 66753,
    "ginkgo": 121484,
    "d2s": 3575,
    "toco": 15029,
    "lisa": 118050,
    "courbet": 20992,
    "oscar": 9527,
    "beryllium": 118315,
    "lunaa": 7824,
    "r5x": 6587,
    "RMX2020": 17323,
    "alioth": 136566,
    "pdx206": 3831,
    "beyondx": 1496,
    "davinci": 49177,
    "G": 2076,
    "cupid": 4792,
    "diting": 1970,
    "marble": 9845,
    "bitra": 4091,
    "beyond2lte": 4583,
    "panther": 2796,
    "spaced": 1493,
    "citrus": 3174,
    "yogurt": 1338,
    "cheetah": 1022,
    "surya": 52840,
    "lancelot": 5793,
    "flame": 2764,
    "violet": 21588,
    "lime": 4780,
    "dubai": 1837,
    "coral": 1802,
    "hotdog": 1165,
    "starlte": 338,
    "whyred": 3833,
    "crownlte": 465,
    "hotdogg": 907,
    "RMX1941": 2271,
    "star2lte": 882,
    "juice": 8761,
    "mojito": 22051
}