{
    "courbet": 12817,
    "coral": 829,
    "flame": 1076,
    "d1": 358,
    "lime": 3663,
    "lisa": 78797,
    "spaced": 1186,
    "sweet": 155927,
    "beyond2lte": 859,
    "vayu": 21270,
    "bitra": 2282,
    "G": 732,
    "toco": 8887,
    "alioth": 59586,
    "RMX2020": 10413,
    "r5x": 6191,
    "lancelot": 3334,
    "ginkgo": 74369,
    "surya": 50369,
    "cepheus": 31478,
    "beyond1lte": 696,
    "munch": 9982,
    "mido": 17609,
    "f62": 363,
    "lunaa": 656,
    "d2s": 849,
    "violet": 16429,
    "panther": 1138,
    "miatoll": 30559,
    "d2x": 478,
    "dubai": 1540,
    "yogurt": 831,
    "beyond0lte": 654,
    "martini": 7755,
    "porsche": 2378,
    "tundra": 0,
    "citrus": 2476,
    "gauguin": 11615,
    "beyondx": 339,
    "beryllium": 65281,
    "davinci": 29201,
    "mojito": 81453,
    "juice": 16055,
    "whyred": 3542,
    "hotdog": 1128,
    "hotdogg": 813,
    "starlte": 274,
    "crownlte": 427,
    "star2lte": 662,
    "RMX1941": 1740
}