{
    "davinci": 44929,
    "marble": 9038,
    "d1": 1184,
    "vayu": 47725,
    "d2s": 3135,
    "sky": 6639,
    "martini": 16339,
    "gauguin": 26324,
    "d2x": 1982,
    "sunny": 31571,
    "oscar": 7722,
    "apollo": 4431,
    "ginkgo": 116009,
    "r5x": 6551,
    "courbet": 18193,
    "beyond2lte": 3875,
    "porsche": 9449,
    "beyond1lte": 3076,
    "alioth": 124178,
    "cepheus": 62870,
    "toco": 14098,
    "miatoll": 56632,
    "G": 2054,
    "tundra": 1614,
    "diting": 1525,
    "RMX2020": 16087,
    "f62": 1552,
    "beyondx": 1060,
    "bitra": 3924,
    "RMX2001L1": 4761,
    "zeus": 2193,
    "beryllium": 107884,
    "guamp": 182,
    "beyond0lte": 2490,
    "sweet": 234848,
    "munch": 18268,
    "cupid": 3526,
    "salaa": 4264,
    "mido": 22281,
    "lisa": 115399,
    "lunaa": 6841,
    "pdx206": 2761,
    "lime": 4695,
    "spaced": 1453,
    "violet": 21262,
    "flame": 2734,
    "coral": 1767,
    "dubai": 1805,
    "cheetah": 991,
    "surya": 52570,
    "lancelot": 5510,
    "panther": 2702,
    "yogurt": 1308,
    "citrus": 3122,
    "crownlte": 459,
    "star2lte": 853,
    "RMX1941": 2186,
    "hotdog": 1163,
    "hotdogg": 894,
    "starlte": 325,
    "whyred": 3778,
    "juice": 8761,
    "mojito": 22051
}