{
    "courbet": 14879,
    "alioth": 83747,
    "beyond2lte": 1655,
    "beyond1lte": 1488,
    "oscar": 964,
    "f62": 731,
    "lisa": 95637,
    "sunny": 6883,
    "G": 1279,
    "d2x": 1017,
    "tundra": 387,
    "d1": 642,
    "salaa": 1191,
    "porsche": 3810,
    "lunaa": 3100,
    "beryllium": 81532,
    "toco": 10730,
    "d2s": 1705,
    "davinci": 35524,
    "mido": 20632,
    "pdx206": 1264,
    "miatoll": 38567,
    "gauguin": 17506,
    "ginkgo": 83813,
    "sky": 826,
    "sweet": 184986,
    "marble": 2774,
    "RMX2001L1": 531,
    "martini": 10566,
    "RMX2020": 13007,
    "beyond0lte": 1282,
    "vayu": 35080,
    "munch": 14763,
    "cepheus": 44818,
    "beyondx": 578,
    "flame": 2453,
    "juice": 16686,
    "cheetah": 831,
    "dubai": 1686,
    "lime": 4388,
    "bitra": 2535,
    "lancelot": 4339,
    "panther": 2320,
    "violet": 20073,
    "r5x": 6394,
    "coral": 1588,
    "surya": 51505,
    "spaced": 1316,
    "yogurt": 1254,
    "citrus": 2979,
    "whyred": 3591,
    "star2lte": 708,
    "crownlte": 435,
    "starlte": 279,
    "hotdog": 1138,
    "RMX1941": 1907,
    "hotdogg": 833,
    "mojito": 22051
}