{
    "alioth": 19807,
    "davinci": 17263,
    "toco": 3668,
    "mido": 11611,
    "sweet": 76659,
    "martini": 981,
    "courbet": 6288,
    "RMX2020": 5555,
    "cepheus": 11077,
    "vayu": 11117,
    "violet": 4396,
    "bitra": 427,
    "lisa": 37858,
    "gauguin": 4632,
    "munch": 784,
    "r5x": 1589,
    "beryllium": 24075,
    "miatoll": 12818,
    "surya": 21508,
    "juice": 11449,
    "ginkgo": 39619,
    "mojito": 40149,
    "star2lte": 447,
    "hotdog": 1062,
    "hotdogg": 651,
    "starlte": 248,
    "crownlte": 406,
    "RMX1941": 894,
    "whyred": 3404
}