{
    "spaced": 1206,
    "beyondx": 367,
    "munch": 10300,
    "tundra": 0,
    "beryllium": 67740,
    "f62": 386,
    "d2x": 533,
    "miatoll": 32522,
    "juice": 16160,
    "citrus": 2645,
    "coral": 1088,
    "davinci": 29854,
    "d2s": 941,
    "gauguin": 12566,
    "porsche": 2576,
    "beyond1lte": 827,
    "violet": 17527,
    "dubai": 1596,
    "beyond2lte": 924,
    "cepheus": 33419,
    "panther": 1598,
    "courbet": 13319,
    "yogurt": 929,
    "sweet": 158563,
    "mido": 17641,
    "lunaa": 1239,
    "vayu": 23174,
    "toco": 9237,
    "r5x": 6246,
    "cheetah": 273,
    "bitra": 2346,
    "mojito": 83723,
    "G": 838,
    "alioth": 61596,
    "ginkgo": 76078,
    "d1": 404,
    "RMX2020": 11008,
    "flame": 1456,
    "lancelot": 3484,
    "beyond0lte": 710,
    "lisa": 81821,
    "surya": 50608,
    "lime": 3939,
    "martini": 8076,
    "hotdogg": 819,
    "whyred": 3550,
    "starlte": 274,
    "hotdog": 1128,
    "crownlte": 427,
    "star2lte": 678,
    "RMX1941": 1783
}