{
    "maintainer": [
        {
            "display_name": "Vantom",
            "telegram": "https://t.me/Vantom",
            "github": "https://github.com/vantoman"
        },
        {
            "display_name": "Aryan",
            "telegram": "https://t.me/Aryannn999",
            "github": "https://github.com/basamaryan"
        }
    ],
    "updater": false,
    "beta": false,
    "version": "thirteen",
    "available_versions": [
        "twelve",
        "thirteen"
    ],
    "release": "monthly",
    "device_display_name": "Xiaomi 11 Lite 4G",
    "device_display_codename": "courbet",
    "public_download": "https://sourceforge.net/projects/pixelos-releases/files/thirteen/courbet/",
    "last_updated": "11 May 2023",
    "private_download_tag": "courbet_20230510_2150",
    "active": true,
    "customRecoveryRequired": true,
    "xda": null
}
