{
    "maintainer": [
        {
            "display_name": "Fellipe Lima",
            "telegram": "https://t.me/Jubscleisson",
            "github": "https://github.com/Jubscleisson"
        }
    ],
    "updater": true,
    "beta": false,
    "version": "fourteen",
    "available_versions": [
        "thirteen",
        "fourteen"
    ],
    "release": "monthly",
    "device_display_name": "Samsung Galaxy Note10+",
    "device_display_codename": "d2s",
    "public_download": "https://sourceforge.net/projects/pixelos-releases/files/fourteen/d2s/",
    "last_updated": "21 September 2024",
    "private_download_tag": "d2s_202409201512",
    "active": true,
    "xda": "https://xdaforums.com/t/rom-14-0-official-pixelos-aosp-encryption-stable-12-05-2024.4506557/",
    "customRecoveryRequired": true
}