{
    "maintainer": [
        {
            "display_name": "Karan Parashar",
            "telegram": "https://t.me/whyredfire",
            "github": "https://github.com/whyredfire"
        }
    ],
    "updater": true,
    "beta": false,
    "version": "thirteen",
    "available_versions": [
        "twelve",
        "thirteen"
    ],
    "release": "monthly",
    "device_display_name": "Xiaomi 11 Lite 5G NE",
    "device_display_codename": "lisa",
    "public_download": "https://sourceforge.net/projects/pixelos-releases/files/thirteen/lisa/",
    "last_updated": "05 July 2023",
    "private_download_tag": "lisa_20230705_0650",
    "active": true,
    "customRecoveryRequired": true,
    "xda": "https://forum.xda-developers.com/t/rom-12-official-pixelos-aosp-stable-23-01-2022.4392297/"
}