{
    "maintainer": [
        {
            "display_name": "Mia Ryujin",
            "telegram": "https://t.me/AISeraphine3_3",
            "github": "https://github.com/Seraphine3"
        }
    ],
    "updater": true,
    "beta": false,
    "version": "twelve",
    "available_versions": [
        "twelve"
    ],
    "release": "monthly",
    "device_display_name": "Samsung Galaxy S9+",
    "device_display_codename": "star2lte",
    "public_download": "https://sourceforge.net/projects/pixelos-releases/files/twelve/star2lte/",
    "last_updated": "14 August 2022",
    "private_download_tag": "star2lte_20220814_1112",
    "active": false,
    "customRecoveryRequired": false,
    "xda": "https://forum.xda-developers.com/t/rom-12l-oss-official-pixel-os-for-samsung-galaxy-s9-s9.4438215/#post-87043351/"
}